maccor_utility/__init__.py
maccor_utility/helper_functions.py
maccor_utility/lookup.py
maccor_utility/read.py
maccor_utility/maccor_dll/MacReadDataFileLIB 64 bit/.gitkeep
maccor_utility-1.4.2.dist-info/licenses/LICENSE.txt
maccor_utility-1.4.2.dist-info/METADATA
maccor_utility-1.4.2.dist-info/WHEEL
maccor_utility-1.4.2.dist-info/top_level.txt
maccor_utility-1.4.2.dist-info/RECORD
