Metadata-Version: 2.4
Name: maccor-utility
Version: 1.4.2
Summary: Utility tools for processing Maccor battery tester data
Home-page: https://github.com/OpenBattTools/maccor-utility
Author: Lukas Gold
Author-email: lukas.gold@isc.fraunhofer.de
License: AGPL-3.0-or-later
Project-URL: Documentation, https://github.com/OpenBattTools/maccor-utility
Project-URL: Source, https://github.com/OpenBattTools/maccor-utility
Platform: Windows
Classifier: Development Status :: 3 - Alpha
Classifier: Programming Language :: Python
Requires-Python: >=3.8
License-File: LICENSE.txt
Requires-Dist: batt-utility>=0.1.3
Requires-Dist: pandas
Requires-Dist: pathlib
Requires-Dist: pydantic
Requires-Dist: pywin32; platform_system == "Windows"
Requires-Dist: strenum; python_version < "3.11"
Requires-Dist: typing_extensions
Provides-Extra: dev
Requires-Dist: pre-commit; extra == "dev"
Provides-Extra: testing
Requires-Dist: setuptools; extra == "testing"
Requires-Dist: pytest; extra == "testing"
Requires-Dist: pytest-cov; extra == "testing"
Dynamic: license-file
